cpimerge/__init__.py
cpimerge/__main__.py
cpimerge/config.py
cpimerge/descriptions.py
cpimerge/exclusions.py
cpimerge/gui.py
cpimerge/ical.py
cpimerge/load.py
cpimerge/merge.py
cpimerge-0.4.4.dist-info/METADATA
cpimerge-0.4.4.dist-info/WHEEL
cpimerge-0.4.4.dist-info/entry_points.txt
cpimerge-0.4.4.dist-info/licenses/LICENSE
cpimerge-0.4.4.dist-info/RECORD
