Metadata-Version: 2.3
Name: cpimerge
Version: 0.4.4
Summary: Merge iCal files generated by CPI
Project-URL: Homepage, https://github.com/kcoombs/cpimerge
Author-email: Kirk Coombs <cpimerge@coombscloud.com>
License-File: LICENSE
Classifier: License :: OSI Approved :: MIT License
Classifier: Operating System :: OS Independent
Classifier: Programming Language :: Python :: 3
Requires-Python: >=3.8
Requires-Dist: appdirs
Requires-Dist: icalendar
